bagel2/__init__.py
bagel2/__main__.py
bagel2/app.py
bagel2/app2.py
bagel2/downloader.py
bagel2/downloader2.py
bagel2/inferencer.py
bagel2/data/__init__.py
bagel2/data/data_utils.py
bagel2/data/dataset_base.py
bagel2/data/dataset_info.py
bagel2/data/distributed_iterable_dataset.py
bagel2/data/parquet_utils.py
bagel2/data/t2i_dataset.py
bagel2/data/transforms.py
bagel2/data/video_utils.py
bagel2/data/vlm_dataset.py
bagel2/data/configs/example.yaml
bagel2/data/interleave_datasets/__init__.py
bagel2/data/interleave_datasets/edit_dataset.py
bagel2/data/interleave_datasets/interleave_t2i_dataset.py
bagel2/eval/__init__.py
bagel2/eval/gen/gen_images_mp.py
bagel2/eval/gen/gen_images_mp_wise.py
bagel2/eval/gen/geneval/evaluation/download_models.sh
bagel2/eval/gen/geneval/evaluation/evaluate_images.py
bagel2/eval/gen/geneval/evaluation/evaluate_images_mp.py
bagel2/eval/gen/geneval/evaluation/object_names.txt
bagel2/eval/gen/geneval/evaluation/summary_scores.py
bagel2/eval/gen/geneval/prompts/create_prompts.py
bagel2/eval/gen/geneval/prompts/evaluation_metadata.jsonl
bagel2/eval/gen/geneval/prompts/evaluation_metadata_long.jsonl
bagel2/eval/gen/geneval/prompts/generation_prompts.txt
bagel2/eval/gen/geneval/prompts/object_names.txt
bagel2/eval/gen/wise/cal_score.py
bagel2/eval/gen/wise/final_data.json
bagel2/eval/gen/wise/gpt_eval_mp.py
bagel2/eval/vlm/__init__.py
bagel2/eval/vlm/evaluate.sh
bagel2/eval/vlm/utils.py
bagel2/eval/vlm/eval/mathvista/calculate_score.py
bagel2/eval/vlm/eval/mathvista/evaluate_mathvista.py
bagel2/eval/vlm/eval/mathvista/extract_answer.py
bagel2/eval/vlm/eval/mathvista/extract_answer_mp.py
bagel2/eval/vlm/eval/mathvista/utilities.py
bagel2/eval/vlm/eval/mathvista/prompts/ext_ans.py
bagel2/eval/vlm/eval/mmbench/evaluate_mmbench.py
bagel2/eval/vlm/eval/mme/calculation.py
bagel2/eval/vlm/eval/mme/eval.py
bagel2/eval/vlm/eval/mme/Your_Results/OCR.txt
bagel2/eval/vlm/eval/mme/Your_Results/artwork.txt
bagel2/eval/vlm/eval/mme/Your_Results/celebrity.txt
bagel2-0.0.6.dist-info/LICENSE
bagel2-0.0.6.dist-info/WHEEL
bagel2-0.0.6.dist-info/METADATA
bagel2-0.0.6.dist-info/RECORD
