Metadata-Version: 2.1
Name: bagel2
Version: 0.0.6
Summary: multimodal-trial-model
Author-email: calcuis <info@calcu.io>
Classifier: License :: OSI Approved :: MIT License
Requires-Dist: pynvml
Project-URL: GitHub, https://github.com/calcuis/multimodal-trial-model
Project-URL: Issues, https://github.com/calcuis/multimodal-trial-model/issues
